README.md
setup.cfg
setup.py
Octopart.egg-info/PKG-INFO
Octopart.egg-info/SOURCES.txt
Octopart.egg-info/dependency_links.txt
Octopart.egg-info/requires.txt
Octopart.egg-info/top_level.txt
octopart/__init__.py
octopart/api.py
octopart/client.py
octopart/decorators.py
octopart/directives.py
octopart/exceptions.py
octopart/models.py
octopart/utils.py
octopart.egg-info/PKG-INFO
octopart.egg-info/SOURCES.txt
octopart.egg-info/dependency_links.txt
octopart.egg-info/requires.txt
octopart.egg-info/top_level.txt